cursor_manager-1.0.9.dist-info/licenses/LICENSE
src/__init__.py
src/cli/__init__.py
src/cli/app.py
src/cli/menu.py
src/core/__init__.py
src/core/cursor_cleaner.py
src/core/cursor_downloader.py
src/core/cursor_manager.py
src/core/update_disabler.py
src/utils/__init__.py
src/utils/browser_handler.py
src/utils/colorful_logger.py
src/utils/console.py
src/utils/system.py
cursor_manager-1.0.9.dist-info/METADATA
cursor_manager-1.0.9.dist-info/WHEEL
cursor_manager-1.0.9.dist-info/entry_points.txt
cursor_manager-1.0.9.dist-info/top_level.txt
cursor_manager-1.0.9.dist-info/RECORD
