Metadata-Version: 2.4
Name: cursor-manager
Version: 1.0.9
Summary: Cursor IDE Manager
Author-email: ovftank <ovftank@gmail.com>
License: Copyright 2025 ovftank
Project-URL: Homepage, https://ovfteam.com
Project-URL: Repository, https://github.com/ovftank/cursor-reset-trial/tree/cli
Requires-Python: >=3.10
License-File: LICENSE
Requires-Dist: requests
Requires-Dist: tqdm
Requires-Dist: psutil
Requires-Dist: questionary
Requires-Dist: rich
Requires-Dist: typer
Requires-Dist: pywin32
Dynamic: license-file
